py_sec_log/__init__.py
py_sec_log/pyslog.py
py_sec_log-0.1.1.2.6.dist-info/LICENSE
py_sec_log-0.1.1.2.6.dist-info/METADATA
py_sec_log-0.1.1.2.6.dist-info/WHEEL
py_sec_log-0.1.1.2.6.dist-info/top_level.txt
py_sec_log-0.1.1.2.6.dist-info/RECORD
